proso_events_client-0.0.6-py3.5-nspkg.pth
proso/events/client.py
proso_events_client-0.0.6.data/scripts/proso-events-log-upload
proso_events_client-0.0.6.dist-info/DESCRIPTION.rst
proso_events_client-0.0.6.dist-info/METADATA
proso_events_client-0.0.6.dist-info/RECORD
proso_events_client-0.0.6.dist-info/WHEEL
proso_events_client-0.0.6.dist-info/metadata.json
proso_events_client-0.0.6.dist-info/namespace_packages.txt
proso_events_client-0.0.6.dist-info/top_level.txt
