Metadata-Version: 2.0
Name: proso-events-client
Version: 0.0.6
Summary: Client for "event storage"."
Home-page: UNKNOWN
Author: Jan Karásek
Author-email: xkarase1@fi.muni.cz
License: The MIT License (MIT)
Requires-Dist: mkdocs
Requires-Dist: progressbar2
Requires-Dist: psycopg2
Requires-Dist: pytest-xdist
Requires-Dist: requests
Requires-Dist: simplejson
